STT_Pratyush/__init__.py
stt_pratyush1-0.1.dist-info/METADATA
stt_pratyush1-0.1.dist-info/WHEEL
stt_pratyush1-0.1.dist-info/top_level.txt
stt_pratyush1-0.1.dist-info/RECORD
