Metadata-Version: 2.4
Name: STT_Pratyush1
Version: 0.1
Summary: Speech to Text
Author: Pratyush Manna
Author-email: prottus2004@gmail.com
Dynamic: author
Dynamic: author-email
Dynamic: summary
